{
  "name": "Ganztags",
  "uniqid": "ext.zwiebelgasse.ganztags",
  "version": "10",

  "requiredVersion": "1.8.0",

  "menu": {
    "categorie": "1",
    "icon": "fa fas fa-campground",
    "params": ""
  },

  "adminGroupName": "Admin_Ext_Ganztags",
  "aclGroupName": "ext_ganztags",

  "cron": [
    {
      "typ": "default",
      "class": "extGanztagsCronFetchPupils"
    }
  ],

  "submenu": [
    {
      "title": "Heute",
      "icon": "fas fa-users",
      "url": {
        "page": "ext_ganztags",
        "params": {
          "view": "my"
        }
      },
      "hidden": false,
      "acl": ["isTeacher"]
    },
    {
      "title": "Kalender",
      "icon": "fas fa-users",
      "url": {
        "page": "ext_ganztags",
        "params": {
          "view": "kalender"
        }
      },
      "hidden": false,
      "acl": ["isTeacher"]
    },
    {
      "title": "Schüler",
      "icon": "fas fa-users",
      "url": {
        "page": "ext_ganztags",
        "params": {
          "view": "default"
        }
      },
      "hidden": false,
      "acl": ["isTeacher"]
    },

    {
      "title": "ACL",
      "icon": "fa fa-user-shield",
      "admin": true,
      "url": {
        "page": "ext_ganztags",
        "params": {
          "view": "acl",
          "admin": "true"
        }
      }
    },
    {
      "title": "Einstellungen",
      "icon": "fa fa-cogs",
      "admin": true,
      "url": {
        "page": "ext_ganztags",
        "params": {
          "view": "default",
          "admin": "true"
        }
      }
    },

    {
      "title": "Aktivitäten",
      "icon": "fas fa-campground",
      "url": {
        "page": "ext_ganztags",
        "params": {
          "view": "activity",
          "admin": "true"
        }
      },
      "hidden": false,
      "admin": true
    },
    {
      "title": "Gruppen",
      "icon": "fas fa-users",
      "url": {
        "page": "ext_ganztags",
        "params": {
          "view": "groups",
          "admin": "true"
        }
      },
      "hidden": false,
      "admin": true
    },
    {
      "title": "Team",
      "icon": "fas fa-user",
      "url": {
        "page": "ext_ganztags",
        "params": {
          "view": "leaders",
          "admin": "true"
        }
      },
      "hidden": false,
      "admin": true
    }

  ]

}